pyjoern/__init__.py
pyjoern/__main__.py
pyjoern/client.py
pyjoern/logger.py
pyjoern/mapping.py
pyjoern/server.py
pyjoern/utils.py
pyjoern/cfg/__init__.py
pyjoern/cfg/jil/__init__.py
pyjoern/cfg/jil/block.py
pyjoern/cfg/jil/lifter.py
pyjoern/cfg/jil/statement.py
pyjoern/parsing/__init__.py
pyjoern/parsing/fast_parser.py
pyjoern/parsing/function.py
pyjoern/scala/FastParser.sc
pyjoern-4.0.150.4.dist-info/LICENSE
pyjoern-4.0.150.4.dist-info/METADATA
pyjoern-4.0.150.4.dist-info/WHEEL
pyjoern-4.0.150.4.dist-info/entry_points.txt
pyjoern-4.0.150.4.dist-info/top_level.txt
pyjoern-4.0.150.4.dist-info/RECORD
