Metadata-Version: 2.1
Name: pyjoern
Version: 4.0.150.4
Summary: PyJoern lifts Joern data and APIs into Pythonic form, focused on graph manipulation.
Home-page: https://github.com/mahaloz/pyjoern
License: BSD 2 Clause
Classifier: License :: OSI Approved :: BSD License
Classifier: Programming Language :: Python :: 3
Classifier: Programming Language :: Python :: 3.8
Requires-Python: >=3.8
License-File: LICENSE
Requires-Dist: networkx
Requires-Dist: cpgqls-client
Requires-Dist: cfgutils
Requires-Dist: psutil
Requires-Dist: graphviz
Requires-Dist: pygraphviz
Requires-Dist: toml
Requires-Dist: tqdm
